{
  "project_info": {
    "project_number": "690504686689",
    "firebase_url": "https://proto2-7a130.firebaseio.com",
    "project_id": "proto2-7a130",
    "storage_bucket": "proto2-7a130.appspot.com"
  },
  "client": [
    {
      "client_info": {
        "mobilesdk_app_id": "1:690504686689:android:02401f9aa1f516a07f5e20",
        "android_client_info": {
          "package_name": "com.example.proto2"
        }
      },
      "oauth_client": [
        {
          "client_id": "690504686689-9qlejoomi9m43ggbmcq6gqm4do3ne699.apps.googleusercontent.com",
          "client_type": 1,
          "android_info": {
            "package_name": "com.example.proto2",
            "certificate_hash": "58f2d7b18f0192ff287f3a1b3a70378ecfa997f1"
          }
        },
        {
          "client_id": "690504686689-osje19umv02jj30k1i49fthgrpd6h6fc.apps.googleusercontent.com",
          "client_type": 3
        }
      ],
      "api_key": [
        {
          "current_key": "AIzaSyDJDsWBeoq-Cs3praBarpmvIo8fy8zTzTY"
        }
      ],
      "services": {
        "appinvite_service": {
          "other_platform_oauth_client": [
            {
              "client_id": "690504686689-osje19umv02jj30k1i49fthgrpd6h6fc.apps.googleusercontent.com",
              "client_type": 3
            }
          ]
        }
      }
    }
  ],
  "configuration_version": "1"
}